dictionary/__init__.py
dictionary/dictionary.py
boras_cs453_dictionary-2.0.2.dist-info/METADATA
boras_cs453_dictionary-2.0.2.dist-info/WHEEL
boras_cs453_dictionary-2.0.2.dist-info/top_level.txt
boras_cs453_dictionary-2.0.2.dist-info/RECORD
