Metadata-Version: 2.1
Name: boras-cs453-dictionary
Version: 2.0.2
Summary: UNKNOWN
Author: Bora Çün
License: UNKNOWN
Platform: UNKNOWN
Requires-Python: >=3.8
Requires-Dist: requests (>=2.23.0)
